{
    "name": "SALE",
    "fields": [
        {
            "fieldName": "url",
            "fieldType": "String",
            "fieldValidateRules": [
                "required"
            ]
        },
        {
            "fieldName": "description",
            "fieldType": "String"
        }
    ],
    "relationships": [],
    "changelogDate": "20181024093342",
    "entityTableName": "sale",
    "dto": "mapstruct",
    "pagination": "no",
    "service": "serviceImpl",
    "jpaMetamodelFiltering": false,
    "fluentMethods": true,
    "clientRootFolder": "",
    "applications": "*"
}